{
  "seneste_ændring": {
    "dato": "2025-06-26",
    "ændring": {
      "benzin": "N/A",
      "diesel": "N/A"
    }
  },
  "priser": [
    {
      "selskab": "Circle K",
      "blyfri_92": "​",
      "blyfri_95_e10": "13.99",
      "blyfri_95_plus_e10": "14.89",
      "blyfri_plus_e5": "​",
      "diesel_b7": "13.19",
      "diesel_plus": "14.09",
      "hvo_xtl": "​",
      "el_normal": "​",
      "el_hurtig": "​",
      "el_lyn": "3.59",
      "sidst_opdateret": "26-06-2025 00:00"
    },
    {
      "selskab": "Shell",
      "blyfri_92": "​",
      "blyfri_95_e10": "15.19",
      "blyfri_95_plus_e10": "​",
      "blyfri_plus_e5": "17.39",
      "diesel_b7": "14.39",
      "diesel_plus": "15.29",
      "hvo_xtl": "15.59",
      "el_normal": "​",
      "el_hurtig": "​",
      "el_lyn": "3.49",
      "sidst_opdateret": "26-06-2025 00:00"
    },
    {
      "selskab": "OK",
      "blyfri_92": "​",
      "blyfri_95_e10": "13.89",
      "blyfri_95_plus_e10": "​",
      "blyfri_plus_e5": "15.86",
      "diesel_b7": "13.09",
      "diesel_plus": "​",
      "hvo_xtl": "​",
      "el_normal": "2.49",
      "el_hurtig": "2.99",
      "el_lyn": "3.49",
      "sidst_opdateret": "26-06-2025 00:00"
    },
    {
      "selskab": "Q8",
      "blyfri_92": "​",
      "blyfri_95_e10": "13.99",
      "blyfri_95_plus_e10": "​",
      "blyfri_plus_e5": "15.09",
      "diesel_b7": "13.19",
      "diesel_plus": "14.09",
      "hvo_xtl": "​",
      "el_normal": "3.09",
      "el_hurtig": "​",
      "el_lyn": "3.59",
      "sidst_opdateret": "26-06-2025 00:00"
    },
    {
      "selskab": "F24",
      "blyfri_92": "​",
      "blyfri_95_e10": "13.89",
      "blyfri_95_plus_e10": "​",
      "blyfri_plus_e5": "14.99",
      "diesel_b7": "13.09",
      "diesel_plus": "13.99",
      "hvo_xtl": "​",
      "el_normal": "​",
      "el_hurtig": "​",
      "el_lyn": "3.75",
      "sidst_opdateret": "26-06-2025 00:00"
    },
    {
      "selskab": "Go'on",
      "blyfri_92": "13.86",
      "blyfri_95_e10": "13.89",
      "blyfri_95_plus_e10": "​",
      "blyfri_plus_e5": "​",
      "diesel_b7": "13.09",
      "diesel_plus": "​",
      "hvo_xtl": "​",
      "el_normal": "​",
      "el_hurtig": "​",
      "el_lyn": "​",
      "sidst_opdateret": "26-06-2025 00:00"
    },
    {
      "selskab": "Clever",
      "blyfri_92": "​",
      "blyfri_95_e10": "​",
      "blyfri_95_plus_e10": "​",
      "blyfri_plus_e5": "​",
      "diesel_b7": "​",
      "diesel_plus": "​",
      "hvo_xtl": "​",
      "el_normal": "3.49",
      "el_hurtig": "3.49",
      "el_lyn": "4.99",
      "sidst_opdateret": "26-06-2025 00:00"
    },
    {
      "selskab": "OIL! tank & go",
      "blyfri_92": "​",
      "blyfri_95_e10": "13.89",
      "blyfri_95_plus_e10": "​",
      "blyfri_plus_e5": "​",
      "diesel_b7": "13.09",
      "diesel_plus": "​",
      "hvo_xtl": "14.09",
      "el_normal": "​",
      "el_hurtig": "​",
      "el_lyn": "​",
      "sidst_opdateret": "25-06-2025 12:00"
    },
    {
      "selskab": "ingo",
      "blyfri_92": "​",
      "blyfri_95_e10": "13.89",
      "blyfri_95_plus_e10": "14.58",
      "blyfri_plus_e5": "​",
      "diesel_b7": "13.09",
      "diesel_plus": "​",
      "hvo_xtl": "​",
      "el_normal": "​",
      "el_hurtig": "​",
      "el_lyn": "​",
      "sidst_opdateret": "25-06-2025 11:00"
    }
  ]
}