{
  "seneste_ændring": {
    "dato": "2025-04-09",
    "ændring": {
      "benzin": "N/A",
      "diesel": "N/A"
    }
  },
  "priser": [
    {
      "selskab": "Shell",
      "blyfri_92": "​",
      "blyfri_95_e10": "15.19",
      "blyfri_95_plus_e10": "​",
      "blyfri_plus_e5": "17.39",
      "diesel_b7": "14.19",
      "diesel_plus": "15.09",
      "hvo_xtl": "15.39",
      "el_normal": "​",
      "el_hurtig": "​",
      "el_lyn": "3.75",
      "sidst_opdateret": "10-04-2025 00:00"
    },
    {
      "selskab": "OK",
      "blyfri_92": "​",
      "blyfri_95_e10": "13.89",
      "blyfri_95_plus_e10": "​",
      "blyfri_plus_e5": "15.86",
      "diesel_b7": "12.89",
      "diesel_plus": "​",
      "hvo_xtl": "​",
      "el_normal": "2.80",
      "el_hurtig": "3.30",
      "el_lyn": "3.80",
      "sidst_opdateret": "10-04-2025 00:00"
    },
    {
      "selskab": "Q8",
      "blyfri_92": "​",
      "blyfri_95_e10": "13.99",
      "blyfri_95_plus_e10": "​",
      "blyfri_plus_e5": "15.06",
      "diesel_b7": "12.99",
      "diesel_plus": "13.79",
      "hvo_xtl": "​",
      "el_normal": "3.19",
      "el_hurtig": "​",
      "el_lyn": "3.90",
      "sidst_opdateret": "10-04-2025 00:00"
    },
    {
      "selskab": "F24",
      "blyfri_92": "​",
      "blyfri_95_e10": "13.89",
      "blyfri_95_plus_e10": "​",
      "blyfri_plus_e5": "14.96",
      "diesel_b7": "12.89",
      "diesel_plus": "13.69",
      "hvo_xtl": "​",
      "el_normal": "​",
      "el_hurtig": "​",
      "el_lyn": "3.75",
      "sidst_opdateret": "10-04-2025 00:00"
    },
    {
      "selskab": "Go'on",
      "blyfri_92": "13.86",
      "blyfri_95_e10": "13.89",
      "blyfri_95_plus_e10": "​",
      "blyfri_plus_e5": "​",
      "diesel_b7": "12.89",
      "diesel_plus": "​",
      "hvo_xtl": "​",
      "el_normal": "​",
      "el_hurtig": "​",
      "el_lyn": "​",
      "sidst_opdateret": "10-04-2025 00:00"
    },
    {
      "selskab": "Clever",
      "blyfri_92": "​",
      "blyfri_95_e10": "​",
      "blyfri_95_plus_e10": "​",
      "blyfri_plus_e5": "​",
      "diesel_b7": "​",
      "diesel_plus": "​",
      "hvo_xtl": "​",
      "el_normal": "3.49",
      "el_hurtig": "3.49",
      "el_lyn": "4.99",
      "sidst_opdateret": "10-04-2025 00:00"
    },
    {
      "selskab": "OIL! tank & go",
      "blyfri_92": "​",
      "blyfri_95_e10": "13.89",
      "blyfri_95_plus_e10": "​",
      "blyfri_plus_e5": "​",
      "diesel_b7": "12.89",
      "diesel_plus": "​",
      "hvo_xtl": "13.89",
      "el_normal": "​",
      "el_hurtig": "​",
      "el_lyn": "​",
      "sidst_opdateret": "08-04-2025 11:00"
    },
    {
      "selskab": "Circle K",
      "blyfri_92": "​",
      "blyfri_95_e10": "13.99",
      "blyfri_95_plus_e10": "14.79",
      "blyfri_plus_e5": "​",
      "diesel_b7": "12.99",
      "diesel_plus": "13.79",
      "hvo_xtl": "​",
      "el_normal": "​",
      "el_hurtig": "​",
      "el_lyn": "3.90",
      "sidst_opdateret": "08-04-2025 00:00"
    },
    {
      "selskab": "ingo",
      "blyfri_92": "​",
      "blyfri_95_e10": "13.89",
      "blyfri_95_plus_e10": "14.38",
      "blyfri_plus_e5": "​",
      "diesel_b7": "12.89",
      "diesel_plus": "​",
      "hvo_xtl": "​",
      "el_normal": "​",
      "el_hurtig": "​",
      "el_lyn": "​",
      "sidst_opdateret": "07-04-2025 11:00"
    }
  ]
}